pgseqmover/__init__.py
pgseqmover/__main__.py
pgseqmover/main.py
pg_sequence_increaser-0.2.dist-info/LICENSE
pg_sequence_increaser-0.2.dist-info/METADATA
pg_sequence_increaser-0.2.dist-info/WHEEL
pg_sequence_increaser-0.2.dist-info/entry_points.txt
pg_sequence_increaser-0.2.dist-info/top_level.txt
pg_sequence_increaser-0.2.dist-info/RECORD
