Metadata-Version: 2.1
Name: pg-sequence-increaser
Version: 0.2
Summary: Set all sequences to a higher value when promoting a PostgreSQL logical replica
Home-page: https://github.com/levkk/pg-sequence-increaser
Author: Lev Kokotov
Author-email: lev.kokotov@instacart.com
License: UNKNOWN
Platform: UNKNOWN
Classifier: Programming Language :: Python :: 3
Classifier: License :: OSI Approved :: MIT License
Classifier: Operating System :: OS Independent
Requires-Python: >=3
Requires-Dist: Click (>=7.0)
Requires-Dist: colorama (>=0.4.3)
Requires-Dist: psycopg2 (>=2.8.4)
